discord_economy/__init__.py
discord_economy/economy.py
discord_economy-0.0.2.dist-info/METADATA
discord_economy-0.0.2.dist-info/WHEEL
discord_economy-0.0.2.dist-info/top_level.txt
discord_economy-0.0.2.dist-info/RECORD
