Metadata-Version: 2.1
Name: discord-economy
Version: 0.0.2
Summary: Make economy much easier
Home-page: UNKNOWN
Author: sldless
License: MIT
Platform: UNKNOWN
Classifier: Programming Language :: Python :: 3
Classifier: License :: OSI Approved :: MIT License
Classifier: Operating System :: OS Independent
Requires-Python: >=3.8
Requires-Dist: pymongo
Requires-Dist: py-cord
